Compiled from "Hello.java"
public class com.MethodInvokeTest.test1.Hello {
  public com.MethodInvokeTest.test1.Hello();
    Code:
       0: aload_0
       1: invokespecial #1                  // Method java/lang/Object."<init>":()V
       4: return

  public static void sayHello();
    Code:
       0: getstatic     #2                  // Field java/lang/System.out:Ljava/io/PrintStream;
       3: ldc           #3                  // String Hello !
       5: invokevirtual #4                  // Method java/io/PrintStream.println:(Ljava/lang/String;)V
       8: return

  public static void main(java.lang.String[]);
    Code:
       0: invokestatic  #5                  // Method sayHello:()V ;即在编译期间已经确定了,这种调用就称为解析调用
       3: return
}
