Compiled from "Demo.java"
public class com.MethodInvokeTest.test2.Demo {
  public com.MethodInvokeTest.test2.Demo();
    Code:
       0: aload_0
       1: invokespecial #1                  // Method java/lang/Object."<init>":()V
       4: return

  public void sayHello(com.MethodInvokeTest.test2.Demo$Child1);
    Code:
       0: getstatic     #2                  // Field java/lang/System.out:Ljava/io/PrintStream;
       3: ldc           #3                  // String child1 is call
       5: invokevirtual #4                  // Method java/io/PrintStream.println:(Ljava/lang/String;)V
       8: return

  public void sayHello(com.MethodInvokeTest.test2.Demo$Child2);
    Code:
       0: getstatic     #2                  // Field java/lang/System.out:Ljava/io/PrintStream;
       3: ldc           #5                  // String child2 is call
       5: invokevirtual #4                  // Method java/io/PrintStream.println:(Ljava/lang/String;)V
       8: return

  public void sayHello(com.MethodInvokeTest.test2.Demo$Parent);
    Code:
       0: getstatic     #2                  // Field java/lang/System.out:Ljava/io/PrintStream;
       3: ldc           #6                  // String parent is call
       5: invokevirtual #4                  // Method java/io/PrintStream.println:(Ljava/lang/String;)V
       8: return

  public static void main(java.lang.String[]);
    Code:
       0: new           #7                  // class com/MethodInvokeTest/test2/Demo$Child1
       3: dup
       4: invokespecial #8                  // Method com/MethodInvokeTest/test2/Demo$Child1."<init>":()V
       7: astore_1
       8: new           #9                  // class com/MethodInvokeTest/test2/Demo$Child2
      11: dup
      12: invokespecial #10                 // Method com/MethodInvokeTest/test2/Demo$Child2."<init>":()V
      15: astore_2
      16: new           #11                 // class com/MethodInvokeTest/test2/Demo
      19: dup
      20: invokespecial #12                 // Method "<init>":()V
      23: astore_3
      24: aload_3
      25: aload_1
      26: invokevirtual #13                 // Method sayHello:(Lcom/MethodInvokeTest/test2/Demo$Parent;)V
      29: aload_3
      30: aload_2
      31: invokevirtual #13                 // Method sayHello:(Lcom/MethodInvokeTest/test2/Demo$Parent;)V
      34: return
}
